MANIFEST.in
README.rst
setup.py
fatbox_django_utils.egg-info/PKG-INFO
fatbox_django_utils.egg-info/SOURCES.txt
fatbox_django_utils.egg-info/dependency_links.txt
fatbox_django_utils.egg-info/requires.txt
fatbox_django_utils.egg-info/top_level.txt
fatbox_utils/__init__.py
fatbox_utils/cache.py
fatbox_utils/context_processors.py
fatbox_utils/decorators.py
fatbox_utils/humanize.py
fatbox_utils/i18n.py
fatbox_utils/middleware.py
fatbox_utils/templatetags/__init__.py
fatbox_utils/templatetags/menu_active_parent.py
fatbox_utils/templatetags/smart_spaceless.py
fatbox_utils/templatetags/urltools.py