Metadata-Version: 1.0
Name: fatbox-django-utils
Version: 1.2
Summary: A collection of Django utilities, built by FatBox
Home-page: https://github.com/fatbox/fatbox-django-utils
Author: Evan Borgstrom
Author-email: evan@fatbox.ca
License: UNKNOWN
Platform: UNKNOWN
Classifier: Development Status :: 5 - Production/Stable
Classifier: Framework :: Django
Classifier: Intended Audience :: Developers
Classifier: License :: OSI Approved :: BSD License
Classifier: Natural Language :: English
Classifier: Topic :: Software Development :: Libraries
Classifier: Topic :: Software Development :: Libraries :: Python Modules
